CHANGELOG.md
cmem_plugin_kaggle/__init__.py
cmem_plugin_kaggle/kaggle_import.py
cmem_plugin_kaggle-2.0.1.dist-info/LICENSE
cmem_plugin_kaggle-2.0.1.dist-info/METADATA
cmem_plugin_kaggle-2.0.1.dist-info/WHEEL
cmem_plugin_kaggle-2.0.1.dist-info/RECORD
