Metadata-Version: 2.1
Name: cmem-plugin-kaggle
Version: 2.0.1
Summary: Import dataset resources from Kaggle.
Home-page: https://github.com/eccenca/cmem-plugin-kaggle
License: Apache-2.0
Keywords: eccenca Corporate Memory,plugin,kaggle,dataset
Author: eccenca GmbH
Author-email: cmempy-developer@eccenca.com
Requires-Python: >=3.11,<4.0
Classifier: Development Status :: 5 - Production/Stable
Classifier: Environment :: Plugins
Classifier: Intended Audience :: Information Technology
Classifier: License :: OSI Approved :: Apache Software License
Classifier: Programming Language :: Python :: 3
Classifier: Programming Language :: Python :: 3.11
Classifier: Programming Language :: Python :: 3.12
Classifier: Programming Language :: Python :: 3.13
Classifier: Topic :: Software Development :: Libraries :: Python Modules
Requires-Dist: cmem-plugin-base (>=4.7.0,<5.0.0)
Requires-Dist: kaggle (>=1.6.17,<2.0.0)
